ki_util/__init__.py
ki_util/atmos.py
ki_util/constants.py
ki_util/geometry.py
ki_util/helpers.py
ki_util/tests/__init__.py
ki_util/tests/test_atmos.py
ki_util/tests/test_geometry.py
ki_util/tests/test_units.py
ki_util/units.py
ki_util-0.2.0.dist-info/LICENSE
ki_util-0.2.0.dist-info/METADATA
ki_util-0.2.0.dist-info/WHEEL
ki_util-0.2.0.dist-info/RECORD
