Metadata-Version: 2.3
Name: ki_util
Version: 0.2.0
Summary: Common utility functions (e.g. constants and unit conversions).
Author: Shiva Bernath
Author-email: shiva@karmanindustries.com
Requires-Python: >=3.11
Classifier: Programming Language :: Python :: 3
Classifier: Programming Language :: Python :: 3.11
Classifier: Programming Language :: Python :: 3.12
Classifier: Programming Language :: Python :: 3.13
Requires-Dist: datetime (>=5.5,<6.0)
Requires-Dist: numpy (>=2.3.1,<3.0.0)
Requires-Dist: pandas (>=2.3.1,<3.0.0)
Requires-Dist: pint (>=0.24.4,<0.25.0)
Requires-Dist: pytest (>=8.4.1,<9.0.0)
Requires-Dist: sphinx (>=8.2.3,<9.0.0)
